risc_v/top_modules_cores/data_memory.v
`timescale 1ps/1ps

// 16-byte data memory. The testbench may preload memory[] hierarchically.
module data_memory(
    input wire clk,
    input wire writeenable,
    input wire [7:0] address,
    input wire [7:0] writedata,
    output wire [7:0] readdata
);
    reg [7:0] memory [0:15];
    assign readdata = memory[address[3:0]];

    always @(posedge clk) begin
        if (writeenable)
            memory[address[3:0]] <= writedata;
    end
endmodule

risc_v/top_modules_cores/alu.v
`timescale 1ps/1ps

// The assignment ALU, kept locally so the CPU folder is self-contained.
module alu(
    input wire [7:0] A,
    input wire [7:0] B,
    input wire [3:0] sel,
    output reg [7:0] result,
    output reg carry,
    output wire zero
);
    assign zero = (result == 8'h00);

    always @(*) begin
        carry = 1'b0;
        case (sel)
            4'h0: {carry, result} = A + B;
            4'h1: {carry, result} = A - B;
            4'h2: result = A & B;
            4'h3: result = A | B;
            4'h4: result = A ^ B;
            default: result = 8'h00;
        endcase
    end
endmodule

risc_v/top_modules_cores/register_file_8x8.v
`timescale 1ps/1ps

// Eight 8-bit registers, with two asynchronous read ports and one write port.
module register_file_8x8(
    input  wire       clk,
    input  wire       rst_n,

    //Read register address for ALU operands. i.e. ALU reads these 
    //registers of address here for operands.
    input  wire [2:0] readreg1,
    input  wire [2:0] readreg2,

    //Answer of ALU is written in this register. Also initial values are stored using this.
    input  wire [2:0] writereg,
    input  wire       writeenable,

    //Data to write into register. Either ALU result or operands loaded into registers.
    input  wire [7:0] writedata,

    //Contents of register address readreg1 and readreg2
    output wire [7:0] regout1,
    output wire [7:0] regout2
);

    //8 8bit registers
    reg [7:0] regs [0:7];
    integer i;

    assign regout1 = regs[readreg1];
    assign regout2 = regs[readreg2];

    always @(posedge clk or negedge rst_n) begin
        if (!rst_n) begin
            for (i = 0; i < 8; i = i + 1)
                regs[i] <= 8'h00;
        end else if (writeenable) begin
            regs[writereg] <= writedata;
        end
    end
endmodule

risc_v/top_modules_cores/cu.v
`timescale 1ps/1ps

// Combinational decoder for the small 8-bit student CPU.
module control_unit(
  input wire [15:0] instruction,
  output reg [2:0] readreg1,
  output reg [2:0] readreg2,
  output reg [2:0] writereg,
  output reg writeenable,
  output reg [7:0] immediate,
  output reg [3:0] alu_op,
  output reg alu_uses_immediate,
  output reg memory_read,
  output reg memory_write,
  output reg branch_equal,
  output reg jump,
  output reg halt
);
  wire [3:0] opcode = instruction[15:12];

  always @(*) begin
    readreg1 = instruction[8:6];
    readreg2 = instruction[5:3];
    writereg = instruction[11:9];
    writeenable = 1'b0;
    immediate = {{2{instruction[5]}}, instruction[5:0]};
    alu_op = 4'b0000;
    alu_uses_immediate = 1'b0;
    memory_read = 1'b0;
    memory_write = 1'b0;
    branch_equal = 1'b0;
    jump = 1'b0;
    halt = 1'b0;

    case (opcode)
      4'h0: begin writeenable = 1'b1; alu_op = 4'h0; end
      4'h1: begin writeenable = 1'b1; alu_op = 4'h1; end
      4'h2: begin writeenable = 1'b1; alu_op = 4'h2; end
      4'h3: begin writeenable = 1'b1; alu_op = 4'h3; end
      4'h4: begin writeenable = 1'b1; alu_op = 4'h4; end
      4'h5: begin writeenable = 1'b1; alu_op = 4'h0; alu_uses_immediate = 1'b1; end
      4'h6: begin writeenable = 1'b1; alu_op = 4'h0; alu_uses_immediate = 1'b1; memory_read = 1'b1; end
      4'h7: begin
        readreg2 = instruction[11:9];
        alu_op = 4'h0;
        alu_uses_immediate = 1'b1;
        memory_write = 1'b1;
      end
      4'h8: branch_equal = 1'b1;
      4'h9: jump = 1'b1;
      4'hf: halt = 1'b1;
      default: begin end
    endcase
  end
endmodule

risc_v/top_modules_cores/instruction_memory.v
`timescale 1ps/1ps

// 16-word instruction memory. The testbench loads memory[] directly.
module instruction_memory(
    input  wire [3:0] address,
    output wire [15:0] instruction
);
    reg [15:0] memory [0:15];

    assign instruction = memory[address];
endmodule

risc_v/top_modules_cores/processor.v
`timescale 1ps/1ps

module processor(
	input wire clk,
	input wire rst_n,
	output wire [3:0] pc_out,
	output wire halted
);
	reg [3:0] pc;
	wire [15:0] instruction;
	wire [2:0] readreg1, readreg2, writereg;
	wire writeenable, alu_uses_immediate, memory_read, memory_write;
	wire branch_equal, jump, halt;
	wire [7:0] immediate;
	wire [3:0] alu_op;
	wire [7:0] regout1, regout2;
	wire [7:0] alu_b;
	wire [7:0] alu_result;
	wire [7:0] memory_data;
	wire [7:0] write_data;
	wire alu_carry;
	wire alu_zero;
	reg [3:0] next_pc;
	reg halted_reg;

	instruction_memory imem(.address(pc), .instruction(instruction));
	control_unit cu(
		.instruction(instruction),
        .readreg1(readreg1), 
        .readreg2(readreg2),
		.writereg(writereg), 
        .writeenable(writeenable), 
        .immediate(immediate),
		.alu_op(alu_op), 
        .alu_uses_immediate(alu_uses_immediate),
		.memory_read(memory_read), 
        .memory_write(memory_write),
		.branch_equal(branch_equal), 
        .jump(jump), 
        .halt(halt)
	);
	register_file_8x8 regs(
		.clk(clk), .rst_n(rst_n), 
        .readreg1(readreg1), 
        .readreg2(readreg2),
		.writereg(writereg), 
        .writeenable(writeenable && !halted_reg),
		.writedata(write_data), 
        .regout1(regout1), 
        .regout2(regout2)
	);
	alu datapath_alu(.A(regout1), 
        .B(alu_b), 
        .sel(alu_op),
		.result(alu_result), 
        .carry(alu_carry), 
        .zero(alu_zero));

	data_memory dmem(.clk(clk), 
        .writeenable(memory_write && !halted_reg),
		.address(alu_result), 
        .writedata(regout2), 
        .readdata(memory_data));

	assign alu_b = alu_uses_immediate ? immediate : regout2;
	assign write_data = memory_read ? memory_data : alu_result;
	assign pc_out = pc;
	assign halted = halted_reg;

	always @(*) begin
		next_pc = pc + 1'b1;
		if (branch_equal && (regout1 == regout2))
			next_pc = pc + immediate[3:0];
		if (jump)
			next_pc = instruction[3:0];
	end

	always @(posedge clk or negedge rst_n) begin
		if (!rst_n) begin
			pc <= 4'h0;
			halted_reg <= 1'b0;
		end else if (!halted_reg) begin
			pc <= next_pc;
			if (halt)
				halted_reg <= 1'b1;
		end
	end
endmodule

risc_v/testbenches/processor_tb.v
`timescale 1ps/1ps

module processor_tb;
    reg clk = 1'b0;
    reg rst_n = 1'b0;
    wire [3:0] pc;
    wire halted;

    processor dut(.clk(clk), .rst_n(rst_n), .pc_out(pc), .halted(halted));

    always #5 clk = ~clk;

    initial begin
        $dumpfile("processor_tb.vcd");
        $dumpvars(0, processor_tb);
    end

    initial begin
        // ADDI r1, r0, 5; ADDI r2, r0, 7; ADD r3, r1, r2; ST r3, [r0+1]; HALT
        dut.imem.memory[0] = 16'h5205;
        dut.imem.memory[1] = 16'h5407;
        dut.imem.memory[2] = 16'h0650;
        dut.imem.memory[3] = 16'h7601;
        dut.imem.memory[4] = 16'hf000;
        repeat (2) @(posedge clk);
        rst_n = 1'b1;
        wait (halted);
        #1;
        if (dut.regs.regs[3] !== 8'd12 || dut.dmem.memory[1] !== 8'd12)
            $display("FAIL: r3=%0d memory[1]=%0d", dut.regs.regs[3], dut.dmem.memory[1]);
        else
            $display("PASS: r3=%0d memory[1]=%0d", dut.regs.regs[3], dut.dmem.memory[1]);
        $finish;
    end
endmodule

risc_v/testbenches/processor_tb.vcd
$date
	Tue Sep 08 22:49:13 2026
$end
$version
	Icarus Verilog
$end
$timescale
	1ps
$end
$scope module processor_tb $end
$var wire 4 ! pc [3:0] $end
$var wire 1 " halted $end
$var reg 1 # clk $end
$var reg 1 $ rst_n $end
$scope module dut $end
$var wire 1 # clk $end
$var wire 1 " halted $end
$var wire 4 % pc_out [3:0] $end
$var wire 1 $ rst_n $end
$var wire 3 & writereg [2:0] $end
$var wire 1 ' writeenable $end
$var wire 8 ( write_data [7:0] $end
$var wire 8 ) regout2 [7:0] $end
$var wire 8 * regout1 [7:0] $end
$var wire 3 + readreg2 [2:0] $end
$var wire 3 , readreg1 [2:0] $end
$var wire 1 - memory_write $end
$var wire 1 . memory_read $end
$var wire 8 / memory_data [7:0] $end
$var wire 1 0 jump $end
$var wire 16 1 instruction [15:0] $end
$var wire 8 2 immediate [7:0] $end
$var wire 1 3 halt $end
$var wire 1 4 branch_equal $end
$var wire 1 5 alu_zero $end
$var wire 1 6 alu_uses_immediate $end
$var wire 8 7 alu_result [7:0] $end
$var wire 4 8 alu_op [3:0] $end
$var wire 1 9 alu_carry $end
$var wire 8 : alu_b [7:0] $end
$var reg 1 ; halted_reg $end
$var reg 4 < next_pc [3:0] $end
$var reg 4 = pc [3:0] $end
$scope module cu $end
$var wire 4 > opcode [3:0] $end
$var wire 16 ? instruction [15:0] $end
$var reg 4 @ alu_op [3:0] $end
$var reg 1 6 alu_uses_immediate $end
$var reg 1 4 branch_equal $end
$var reg 1 3 halt $end
$var reg 8 A immediate [7:0] $end
$var reg 1 0 jump $end
$var reg 1 . memory_read $end
$var reg 1 - memory_write $end
$var reg 3 B readreg1 [2:0] $end
$var reg 3 C readreg2 [2:0] $end
$var reg 1 ' writeenable $end
$var reg 3 D writereg [2:0] $end
$upscope $end
$scope module datapath_alu $end
$var wire 8 E B [7:0] $end
$var wire 4 F sel [3:0] $end
$var wire 1 5 zero $end
$var wire 8 G A [7:0] $end
$var reg 1 9 carry $end
$var reg 8 H result [7:0] $end
$upscope $end
$scope module dmem $end
$var wire 8 I address [7:0] $end
$var wire 1 # clk $end
$var wire 8 J readdata [7:0] $end
$var wire 1 K writeenable $end
$var wire 8 L writedata [7:0] $end
$upscope $end
$scope module imem $end
$var wire 4 M address [3:0] $end
$var wire 16 N instruction [15:0] $end
$upscope $end
$scope module regs $end
$var wire 1 # clk $end
$var wire 3 O readreg1 [2:0] $end
$var wire 3 P readreg2 [2:0] $end
$var wire 8 Q regout1 [7:0] $end
$var wire 8 R regout2 [7:0] $end
$var wire 1 $ rst_n $end
$var wire 8 S writedata [7:0] $end
$var wire 1 T writeenable $end
$var wire 3 U writereg [2:0] $end
$var integer 32 V i [31:0] $end
$upscope $end
$upscope $end
$upscope $end
$enddefinitions $end
$comment Show the parameter values. $end
$dumpall
$end
#0
$dumpvars
b1000 V
b1 U
1T
b101 S
b0 R
b0 Q
b0 P
b0 O
b101001000000101 N
b0 M
b0 L
0K
bx J
b101 I
b101 H
b0 G
b0 F
b101 E
b1 D
b0 C
b0 B
b101 A
b0 @
b101001000000101 ?
b101 >
b0 =
b1 <
0;
b101 :
09
b0 8
b101 7
16
05
04
03
b101 2
b101001000000101 1
00
bx /
0.
0-
b0 ,
b0 +
b0 *
b0 )
b101 (
1'
b1 &
b0 %
0$
0#
0"
b0 !
$end
#5
b1000 V
1#
#10
0#
#15
1$
b1000 V
1#
#20
0#
#25
b111 (
b111 S
b111 7
b111 H
b111 I
b111 :
b111 E
16
b111 2
b111 A
1'
b10 &
b10 D
b10 U
b10 <
b101010000000111 1
b101010000000111 ?
b101010000000111 N
b1 !
b1 %
b1 =
b1 M
1#
#30
0#
#35
b1100 (
b1100 S
b111 :
b111 E
b1100 7
b1100 H
b1100 I
b0 >
06
b10000 2
b10000 A
1'
b11 &
b11 D
b11 U
b111 )
b111 L
b111 R
b10 +
b10 C
b10 P
b101 *
b101 G
b101 Q
b1 ,
b1 B
b1 O
b11 <
b11001010000 1
b11001010000 ?
b11001010000 N
b10 !
b10 %
b10 =
b10 M
1#
#40
0#
#45
1K
0T
05
b1 (
b1 S
1-
16
b1 :
b1 E
b1 7
b1 H
b1 I
b111 >
b1 2
b1 A
0'
b1100 )
b1100 L
b1100 R
b11 +
b11 C
b11 P
b0 *
b0 G
b0 Q
b0 ,
b0 B
b0 O
b100 <
b111011000000001 1
b111011000000001 ?
b111011000000001 N
b11 !
b11 %
b11 =
b11 M
1#
#50
0#
#55
b0 (
b0 S
0K
15
b0 7
b0 H
b0 I
13
b0 :
b0 E
b1111 >
0-
06
b0 2
b0 A
b0 &
b0 D
b0 U
b0 )
b0 L
b0 R
b0 +
b0 C
b0 P
b101 <
bx /
bx J
b1111000000000000 1
b1111000000000000 ?
b1111000000000000 N
b100 !
b100 %
b100 =
b100 M
1#
#60
0#
#65
bx (
bx S
bx :
bx E
x9
x5
bx 7
bx H
bx I
bx >
03
bx 2
bx A
bx &
bx D
bx U
bx )
bx L
bx R
bx +
bx C
bx P
bx *
bx G
bx Q
bx ,
bx B
bx O
b110 <
1"
1;
bx 1
bx ?
bx N
b101 !
b101 %
b101 =
b101 M
1#
