Assignment 2 - 8bit ALU/alu.v
module alu(
    input  [7:0] A,
    input  [7:0] B,
    input  [3:0] sel,

    output reg [7:0] result,
    output reg carry,
    output zero
);

always @(*) begin

    carry = 0;

    case(sel)

        4'b0000: begin
            {carry,result} = A + B;
        end

        4'b0001: begin
            {carry,result} = A - B;
        end

        4'b0010: begin
            result = A & B;
        end

        4'b0011: begin
            result = A | B;
        end

        4'b0100: begin
            result = A ^ B;
        end

        4'b0101: begin
            result = ~A;
        end

        4'b0110: begin
            result = A << 1;
        end

        4'b0111: begin
            result = A >> 1;
        end

        4'b1000: begin
            result = A + 1;
        end

        4'b1001: begin
            result = A - 1;
        end

        default: begin
            result = 8'b00000000;
            carry = 0;
        end

    endcase

end


endmodule

Assignment 2 - 8bit ALU/alu_tb.v
`timescale 1ns/1ps

module alu_tb;

reg [7:0] A;
reg [7:0] B;
reg [3:0] sel;

wire [7:0] result;
wire carry;
wire zero;

alu uut(
    .A(A),
    .B(B),
    .sel(sel),
    .result(result),
    .carry(carry),
    .zero(zero)
);

initial begin

    $dumpfile("alu.vcd");
    $dumpvars(0,alu_tb);

    $monitor("Time=%0t A=%d B=%d sel=%b Result=%d Carry=%b Zero=%b",
             $time,A,B,sel,result,carry,zero);

    A = 8'd25;
    B = 8'd10;

    sel = 4'b0000; #10;   // Add
    sel = 4'b0001; #10;   // Sub
    sel = 4'b0010; #10;   // AND
    sel = 4'b0011; #10;   // OR
    sel = 4'b0100; #10;   // XOR
    sel = 4'b0101; #10;   // NOT
    sel = 4'b0110; #10;   // Shift Left
    sel = 4'b0111; #10;   // Shift Right
    sel = 4'b1000; #10;   // Increment
    sel = 4'b1001; #10;   // Decrement

    A = 8'd255;
    B = 8'd1;
    sel = 4'b0000; #10;   // Overflow

    $finish;

end

endmodule

Assignment 2 - 8bit ALU/alu.vcd
$date
	Thu Jul 02 22:15:36 2026
$end
$version
	Icarus Verilog
$end
$timescale
	1ps
$end
$scope module alu_tb $end
$var wire 1 ! zero $end
$var wire 8 " result [7:0] $end
$var wire 1 # carry $end
$var reg 8 $ A [7:0] $end
$var reg 8 % B [7:0] $end
$var reg 4 & sel [3:0] $end
$scope module uut $end
$var wire 8 ' A [7:0] $end
$var wire 8 ( B [7:0] $end
$var wire 4 ) sel [3:0] $end
$var wire 1 ! zero $end
$var reg 1 # carry $end
$var reg 8 * result [7:0] $end
$upscope $end
$upscope $end
$enddefinitions $end
$comment Show the parameter values. $end
$dumpall
$end
#0
$dumpvars
b100011 *
b0 )
b1010 (
b11001 '
b0 &
b1010 %
b11001 $
0#
b100011 "
z!
$end
#10000
b1111 "
b1111 *
b1 &
b1 )
#20000
b1000 "
b1000 *
b10 &
b10 )
#30000
b11011 "
b11011 *
b11 &
b11 )
#40000
b10011 "
b10011 *
b100 &
b100 )
#50000
b11100110 "
b11100110 *
b101 &
b101 )
#60000
b110010 "
b110010 *
b110 &
b110 )
#70000
b1100 "
b1100 *
b111 &
b111 )
#80000
b11010 "
b11010 *
b1000 &
b1000 )
#90000
b11000 "
b11000 *
b1001 &
b1001 )
#100000
1#
b0 "
b0 *
b0 &
b0 )
b1 %
b1 (
b11111111 $
b11111111 '
